notutil/__init__.py
notutil/basic.py
notutil-0.24.5.dist-info/LICENSE
notutil-0.24.5.dist-info/METADATA
notutil-0.24.5.dist-info/WHEEL
notutil-0.24.5.dist-info/top_level.txt
notutil-0.24.5.dist-info/RECORD
