Metadata-Version: 2.1
Name: notutil
Version: 0.24.5
Summary: 小型Python工具包
Author: Not白毛控
Author-email: 231310326@mail.dhu.edu.cn
License-File: LICENSE
